odoo9_addon_donation_base-9.0.1.0.0.99.dev22-py2.7-nspkg.pth
odoo9_addon_donation_base-9.0.1.0.0.99.dev22.dist-info/METADATA
odoo9_addon_donation_base-9.0.1.0.0.99.dev22.dist-info/RECORD
odoo9_addon_donation_base-9.0.1.0.0.99.dev22.dist-info/WHEEL
odoo9_addon_donation_base-9.0.1.0.0.99.dev22.dist-info/namespace_packages.txt
odoo9_addon_donation_base-9.0.1.0.0.99.dev22.dist-info/top_level.txt
odoo_addons/donation_base/README.rst
odoo_addons/donation_base/__init__.py
odoo_addons/donation_base/__openerp__.py
odoo_addons/donation_base/data/donation_mail_template.xml
odoo_addons/donation_base/data/donation_tax_seq.xml
odoo_addons/donation_base/demo/donation_demo.xml
odoo_addons/donation_base/i18n/de.po
odoo_addons/donation_base/i18n/donation_base.pot
odoo_addons/donation_base/i18n/fr.po
odoo_addons/donation_base/models/__init__.py
odoo_addons/donation_base/models/donation_tax_receipt.py
odoo_addons/donation_base/models/partner.py
odoo_addons/donation_base/models/product.py
odoo_addons/donation_base/report/report.xml
odoo_addons/donation_base/report/report_donationtax.xml
odoo_addons/donation_base/security/ir.model.access.csv
odoo_addons/donation_base/security/tax_receipt_security.xml
odoo_addons/donation_base/static/description/icon.png
odoo_addons/donation_base/views/donation_tax_receipt.xml
odoo_addons/donation_base/views/partner.xml
odoo_addons/donation_base/views/product.xml
odoo_addons/donation_base/wizard/__init__.py
odoo_addons/donation_base/wizard/tax_receipt_annual_create.py
odoo_addons/donation_base/wizard/tax_receipt_annual_create_view.xml
odoo_addons/donation_base/wizard/tax_receipt_print.py
odoo_addons/donation_base/wizard/tax_receipt_print_view.xml
